grawl/__init__.py
grawl/__main__.py
grawl/agents/__init__.py
grawl/agents/doc_generator.py
grawl/utils/__init__.py
grawl/utils/file_utils.py
grawl/utils/git.py
grawl-0.1.0.dist-info/licenses/LICENSE
tests/__init__.py
grawl-0.1.0.dist-info/METADATA
grawl-0.1.0.dist-info/WHEEL
grawl-0.1.0.dist-info/entry_points.txt
grawl-0.1.0.dist-info/top_level.txt
grawl-0.1.0.dist-info/RECORD
