Metadata-Version: 2.4
Name: grawl
Version: 0.1.0
Summary: Generate repository documentation for LLMs
Home-page: https://github.com/kacppian/grawl
Author: Kacppian
Author-email: Kacppian <kacppian@example.com>
License: MIT License
Project-URL: Homepage, https://github.com/kacppian/grawl
Project-URL: Issues, https://github.com/kacppian/grawl/issues
Classifier: Programming Language :: Python :: 3
Classifier: Programming Language :: Python :: 3.10
Classifier: License :: OSI Approved :: MIT License
Classifier: Operating System :: OS Independent
Classifier: Development Status :: 3 - Alpha
Classifier: Intended Audience :: Developers
Classifier: Topic :: Software Development :: Documentation
Classifier: Topic :: Software Development :: Libraries :: Python Modules
Requires-Python: >=3.10
License-File: LICENSE
Requires-Dist: openai>=1.10.0
Requires-Dist: openai-agents==0.0.7
Requires-Dist: typer>=0.9.0
Requires-Dist: gitpython>=3.1.40
Requires-Dist: rich>=13.6.0
Requires-Dist: pydantic>=2.5.0
Provides-Extra: dev
Requires-Dist: pytest>=7.0.0; extra == "dev"
Requires-Dist: pytest-cov>=4.0.0; extra == "dev"
Requires-Dist: black>=23.0.0; extra == "dev"
Requires-Dist: isort>=5.12.0; extra == "dev"
Requires-Dist: flake8>=6.0.0; extra == "dev"
Requires-Dist: mypy>=1.0.0; extra == "dev"
Dynamic: author
Dynamic: home-page
Dynamic: license-file
Dynamic: requires-python
